{
    "edits": [
        {
            "original": "Team Fortress 2 2019.07.11 - 18.06.29.01.mp4",
            "new name": "rohan myyyst ceekay adventures",
            "times": [
                "-254"
            ]
        }
    ],
    "renames": {},
    "deletions": [
        "Team Fortress 2 2019.07.13 - 00.11.40.02.DVR.mp4"
    ],
    "paths": {
        "source path": [
            "C:",
            "\\",
            "Users",
            "Sunny",
            "Videos",
            "Team Fortress 2"
        ],
        "renames path": [
            "C:",
            "\\",
            "Users",
            "Sunny",
            "Videos",
            "Renames"
        ],
        "destination path": [
            "C:",
            "\\",
            "Users",
            "Sunny",
            "Videos",
            "Edits"
        ]
    }
}